tfprob/__init__.py
tfprob/version.py
tfprob-0.0.1.dist-info/METADATA
tfprob-0.0.1.dist-info/WHEEL
tfprob-0.0.1.dist-info/top_level.txt
tfprob-0.0.1.dist-info/RECORD
