Metadata-Version: 2.1
Name: tfprob
Version: 0.0.1
Summary: tfprob
Home-page: http://github.com/tensorflow/probability/
Author: Google Inc.
Author-email: packages@tensorflow.org
Classifier: Programming Language :: Python
Classifier: Intended Audience :: Developers
Classifier: Intended Audience :: Education
Classifier: Intended Audience :: Science/Research
